cython_vst_loader/__init__.py
cython_vst_loader/exceptions.py
cython_vst_loader/vst_constants.py
cython_vst_loader/vst_event.py
cython_vst_loader/vst_host.py
cython_vst_loader/vst_loader_wrapper.cp39-win_amd64.pyd
cython_vst_loader/vst_plugin.py
cython_vst_loader/dto/__init__.py
cython_vst_loader/dto/vst_time_info.py
cython_vst_loader-0.3.6.dist-info/LICENSE
cython_vst_loader-0.3.6.dist-info/METADATA
cython_vst_loader-0.3.6.dist-info/WHEEL
cython_vst_loader-0.3.6.dist-info/top_level.txt
cython_vst_loader-0.3.6.dist-info/RECORD
