Metadata-Version: 2.1
Name: cython-vst-loader
Version: 0.3.6
Summary: a cython-based loader for VST audio plugins providing a clean python object-oriented interface
Home-page: https://github.com/hq9000/cython-vst-loader
Author: Sergey Grechin
Author-email: grechin.sergey@gmail.com
License: MIT
Keywords: vst,plugin,cython
Platform: UNKNOWN
Classifier: Development Status :: 4 - Beta
Classifier: Intended Audience :: Developers
Classifier: License :: OSI Approved :: MIT License
Classifier: Programming Language :: Python :: 3
Classifier: Programming Language :: Python :: 3.7
Classifier: Programming Language :: Python :: 3.8
Classifier: Programming Language :: Python :: 3.9
